yourmove_monitor/__init__.py
yourmove_monitor/db.py
yourmove_monitor/tools.py
yourmove_monitor-0.1.2.dist-info/LICENSE
yourmove_monitor-0.1.2.dist-info/METADATA
yourmove_monitor-0.1.2.dist-info/WHEEL
yourmove_monitor-0.1.2.dist-info/top_level.txt
yourmove_monitor-0.1.2.dist-info/RECORD
